struct_ie/__init__.py
struct_ie/models.py
struct_ie-0.0.2.dist-info/LICENSE
struct_ie-0.0.2.dist-info/METADATA
struct_ie-0.0.2.dist-info/WHEEL
struct_ie-0.0.2.dist-info/top_level.txt
struct_ie-0.0.2.dist-info/RECORD
