Metadata-Version: 2.1
Name: struct_ie
Version: 0.0.2
Summary: A Python library for structured information extraction with LLMs.
Author-email: Urchade Zaratiana <urchade.zaratiana@gmail.com>
Maintainer-email: Urchade Zaratiana <urchade.zaratiana@gmail.com>
License: MIT
Project-URL: Homepage, https://github.com/urchade/struct_ie
Project-URL: Repository, https://github.com/urchade/struct_ie
Keywords: named-entity-recognition,ner,data-science,natural-language-processing,artificial-intelligence,nlp,machine-learning,transformers
Requires-Python: >=3.8
License-File: LICENSE
Requires-Dist: pydantic
Requires-Dist: outlines
